frameapp/__init__.py
frameapp/entrypoint.py
frameapp/exceptions.py
frameapp/path.py
frameapp/registry.py
frameapp/schemas.py
frameapp/structures.py
frameapp/util.py
frameapp/configurator/__init__.py
frameapp/configurator/predicates.py
frameapp/configurator/renderers.py
frameapp/configurator/routes.py
frameapp/configurator/sums.py
frameapp/configurator/util.py
frameapp/configurator/views.py
frameapp/ext/__init__.py
frameapp/ext/django_integration/__init__.py
frameapp/ext/django_integration/middleware.py
frameapp/ext/django_integration/url.py
frameapp/ext/django_integration/view.py
frameapp/ext/sphinx_integration/__init__.py
frameapp/ext/sphinx_integration/directives.py
frameapp/marker/__init__.py
frameapp/marker/view.py
frameapp-0.0.3.dist-info/DESCRIPTION.rst
frameapp-0.0.3.dist-info/METADATA
frameapp-0.0.3.dist-info/RECORD
frameapp-0.0.3.dist-info/WHEEL
frameapp-0.0.3.dist-info/metadata.json
frameapp-0.0.3.dist-info/top_level.txt
tests/__init__.py
tests/test_phony.py
